just_agents/tools/__init__.py
just_agents/tools/agents_locator.py
just_agents/tools/db.py
just_agents/tools/interactions.py
just_agents/tools/open_search.py
just_agents/tools/search.py
just_agents/tools/semantic_search.py
just_agents/tools/weather.py
just_agents_tools-0.8.7.dist-info/METADATA
just_agents_tools-0.8.7.dist-info/WHEEL
just_agents_tools-0.8.7.dist-info/RECORD
